examples/benchmark_tracking.py
examples/geometric_calibration.py
examples/kalman_filter.py
examples/photometric_calibration.py
gsoup/FreeMono.ttf
gsoup/__init__.py
gsoup/core.py
gsoup/geometry_advanced.py
gsoup/geometry_basic.py
gsoup/gsoup_io.py
gsoup/image.py
gsoup/procam.py
gsoup/projector_plugin_mitsuba.py
gsoup/rasterize.py
gsoup/sphere_trace.py
gsoup/structures.py
gsoup/track.py
gsoup/track_orig.py
gsoup/transforms.py
gsoup/video.py
gsoup/viewer.py
gsoup/viewer_drivers.py
gsoup-0.2.9.dist-info/licenses/LICENSE
gsoup-0.2.9.dist-info/METADATA
gsoup-0.2.9.dist-info/WHEEL
gsoup-0.2.9.dist-info/top_level.txt
gsoup-0.2.9.dist-info/RECORD
