Metadata-Version: 2.4
Name: gsoup
Version: 0.2.9
Summary: A geoemtry & graphics library with focus on clarity rather than performance.
Author-email: Yotam Erel <erelyotam@gmail.com>
License: MIT License
Project-URL: Homepage, https://github.com/yoterel/gsoup
Keywords: geometry,graphics,autograd,vision
Classifier: License :: OSI Approved :: MIT License
Classifier: Programming Language :: Python
Classifier: Programming Language :: Python :: 3
Requires-Python: >=3.8
License-File: LICENSE
Requires-Dist: torch>=1.10
Requires-Dist: numpy
Requires-Dist: Pillow
Requires-Dist: scipy
Requires-Dist: opencv-python-headless
Requires-Dist: OpenEXR>=3.3.0
Requires-Dist: mitsuba
Provides-Extra: build
Requires-Dist: build; extra == "build"
Requires-Dist: twine; extra == "build"
Provides-Extra: dev
Requires-Dist: bumpver; extra == "dev"
Requires-Dist: pytest; extra == "dev"
Provides-Extra: vis
Requires-Dist: polyscope; extra == "vis"
Dynamic: license-file
